mcc_workshop/__init__.py
mcc_workshop/setup.py
mcc_workshop/utils/__init__.py
mcc_workshop/utils/handlers.py
mcc_workshop-0.0.5.dist-info/METADATA
mcc_workshop-0.0.5.dist-info/WHEEL
mcc_workshop-0.0.5.dist-info/top_level.txt
mcc_workshop-0.0.5.dist-info/RECORD
